[{"route":"/slide/demo2/subSlide2","title":"demo of sub-slide 2","sourceFile":"subSlide2.md"},{"route":"/slide/slide-0","order":999,"tilte":"slide1","sourceFile":"slide-0.md"},{"route":"/slide/slide-1","title":"slide-1","sourceFile":"slide-1.md"},{"route":"/slide/slide-2","title":"slide-2","sourceFile":"slide-2.md"},{"route":"/slide/slide-3","title":"slide3","order":999,"sourceFile":"slide-3.md"},{"route":"/slide/slide-4","title":"Four Slide Four","order":100,"sourceFile":"slide-4.md"},{"route":"/slide/slide","title":"Four Slide Four","order":100,"sourceFile":"slide.md"}]